{
    "name": "pxt-bridge-roller-IR",
    "version": "0.1.0",
    "description": "servo controll for wooden bridge toy",
    "dependencies": {
        "core": "*",
        "radio": "*",
        "microphone": "*"
    },
    "files": [
        "README.md",
        "main.blocks",
        "main.ts",
        "servo.ts",
        "semaphor.ts"
    ],
    "testFiles": [
        "test.ts"
    ],
    "public": true,
    "targetVersions": {
        "target": "4.0.17",
        "targetId": "microbit"
    },
    "supportedTargets": [
        "microbit"
    ],
    "preferredEditor": "tsprj"
}
